paddle_ocr_easy/__init__.py
paddle_ocr_easy/ocr.py
paddle_ocr_easy-0.0.3.dist-info/licenses/LICENSE
paddle_ocr_easy-0.0.3.dist-info/METADATA
paddle_ocr_easy-0.0.3.dist-info/WHEEL
paddle_ocr_easy-0.0.3.dist-info/top_level.txt
paddle_ocr_easy-0.0.3.dist-info/RECORD
