Metadata-Version: 2.4
Name: paddle-ocr-easy
Version: 0.0.3
Summary: Simple library to run PaddleOCR easily on images, plot results, and print detected texts.
Author-email: Om Uskaikar <omuskaikar@gmail.com>
License: MIT License
Classifier: Programming Language :: Python :: 3
Classifier: License :: OSI Approved :: MIT License
Classifier: Operating System :: OS Independent
Requires-Python: >=3.7
License-File: LICENSE
Requires-Dist: paddleocr
Requires-Dist: paddlepaddle
Requires-Dist: matplotlib>=3.3.0
Requires-Dist: opencv-python>=4.5.0
Dynamic: license-file
